energy_logger/__about__.py
energy_logger/__init__.py
energy_logger/models.py
energy_logger/settings.py
energy_logger/inputs/__init__.py
energy_logger/inputs/protocols.py
energy_logger/inputs/util.py
energy_logger/inputs/enphase/__init__.py
energy_logger/inputs/enphase/client.py
energy_logger/inputs/goodwe/__init__.py
energy_logger/inputs/homewizard/__init__.py
energy_logger/inputs/homewizard/errors.py
energy_logger/inputs/homewizard/p1/__init__.py
energy_logger/inputs/homewizard/p1/input.py
energy_logger/inputs/homewizard/p1/response.py
energy_logger/inputs/homewizard/p1/settings.py
energy_logger/outputs/__init__.py
energy_logger/outputs/protocols.py
energy_logger-0.0.1.dist-info/METADATA
energy_logger-0.0.1.dist-info/WHEEL
energy_logger-0.0.1.dist-info/licenses/LICENSE.txt
energy_logger-0.0.1.dist-info/RECORD
