Metadata-Version: 2.1
Name: energy-logger
Version: 0.0.1
Summary: Energy logger
Project-URL: Documentation, https://github.com/unknown/energy-logger#readme
Project-URL: Issues, https://github.com/unknown/energy-logger/issues
Project-URL: Source, https://github.com/unknown/energy-logger
Author-email: Marcel Blijleven <marcelblijleven@gmail.com>
License-Expression: MIT
License-File: LICENSE.txt
Classifier: Development Status :: 4 - Beta
Classifier: Programming Language :: Python
Classifier: Programming Language :: Python :: 3.11
Classifier: Programming Language :: Python :: Implementation :: CPython
Classifier: Programming Language :: Python :: Implementation :: PyPy
Requires-Python: >=3.11
Requires-Dist: httpx==0.24.1
Requires-Dist: pydantic-settings==2.0.3
Requires-Dist: pydantic==2.1.1
Requires-Dist: trio==0.22.2
Provides-Extra: docs
Requires-Dist: mkdocs-material==9.1.21; extra == 'docs'
Requires-Dist: mkdocs==1.5.2; extra == 'docs'
Provides-Extra: test
Requires-Dist: pytest-httpx==0.23.1; extra == 'test'
Requires-Dist: pytest==7.4.0; extra == 'test'
Requires-Dist: ruff==0.0.284; extra == 'test'
